{"nodes": [{"id": "c_users_point_projects_stockpredictor_packages_data_tests_test_broker_py", "label": "test_broker.py", "file_type": "code", "source_file": "C:\\Users\\point\\projects\\stockpredictor\\packages\\data\\tests\\test_broker.py", "source_location": "L1"}, {"id": "test_broker_test_broker_enforces_rate_limit", "label": "test_broker_enforces_rate_limit()", "file_type": "code", "source_file": "C:\\Users\\point\\projects\\stockpredictor\\packages\\data\\tests\\test_broker.py", "source_location": "L6"}, {"id": "test_broker_test_broker_raises_for_unknown_source", "label": "test_broker_raises_for_unknown_source()", "file_type": "code", "source_file": "C:\\Users\\point\\projects\\stockpredictor\\packages\\data\\tests\\test_broker.py", "source_location": "L21"}, {"id": "test_broker_test_broker_rate_limits_when_saturated", "label": "test_broker_rate_limits_when_saturated()", "file_type": "code", "source_file": "C:\\Users\\point\\projects\\stockpredictor\\packages\\data\\tests\\test_broker.py", "source_location": "L27"}, {"id": "test_broker_rationale_7", "label": "DataBroker should pace requests to stay within rate limits.", "file_type": "rationale", "source_file": "C:\\Users\\point\\projects\\stockpredictor\\packages\\data\\tests\\test_broker.py", "source_location": "L7"}, {"id": "test_broker_rationale_28", "label": "When burst capacity exceeded, DataBroker should call time.sleep.", "file_type": "rationale", "source_file": "C:\\Users\\point\\projects\\stockpredictor\\packages\\data\\tests\\test_broker.py", "source_location": "L28"}], "edges": [{"source": "c_users_point_projects_stockpredictor_packages_data_tests_test_broker_py", "target": "time", "relation": "imports", "confidence": "EXTRACTED", "source_file": "C:\\Users\\point\\projects\\stockpredictor\\packages\\data\\tests\\test_broker.py", "source_location": "L1", "weight": 1.0}, {"source": "c_users_point_projects_stockpredictor_packages_data_tests_test_broker_py", "target": "pytest", "relation": "imports", "confidence": "EXTRACTED", "source_file": "C:\\Users\\point\\projects\\stockpredictor\\packages\\data\\tests\\test_broker.py", "source_location": "L2", "weight": 1.0}, {"source": "c_users_point_projects_stockpredictor_packages_data_tests_test_broker_py", "target": "unittest_mock", "relation": "imports_from", "confidence": "EXTRACTED", "source_file": "C:\\Users\\point\\projects\\stockpredictor\\packages\\data\\tests\\test_broker.py", "source_location": "L3", "weight": 1.0}, {"source": "c_users_point_projects_stockpredictor_packages_data_tests_test_broker_py", "target": "nq_data_broker", "relation": "imports_from", "confidence": "EXTRACTED", "source_file": "C:\\Users\\point\\projects\\stockpredictor\\packages\\data\\tests\\test_broker.py", "source_location": "L4", "weight": 1.0}, {"source": "c_users_point_projects_stockpredictor_packages_data_tests_test_broker_py", "target": "test_broker_test_broker_enforces_rate_limit", "relation": "contains", "confidence": "EXTRACTED", "source_file": "C:\\Users\\point\\projects\\stockpredictor\\packages\\data\\tests\\test_broker.py", "source_location": "L6", "weight": 1.0}, {"source": "c_users_point_projects_stockpredictor_packages_data_tests_test_broker_py", "target": "test_broker_test_broker_raises_for_unknown_source", "relation": "contains", "confidence": "EXTRACTED", "source_file": "C:\\Users\\point\\projects\\stockpredictor\\packages\\data\\tests\\test_broker.py", "source_location": "L21", "weight": 1.0}, {"source": "c_users_point_projects_stockpredictor_packages_data_tests_test_broker_py", "target": "test_broker_test_broker_rate_limits_when_saturated", "relation": "contains", "confidence": "EXTRACTED", "source_file": "C:\\Users\\point\\projects\\stockpredictor\\packages\\data\\tests\\test_broker.py", "source_location": "L27", "weight": 1.0}, {"source": "test_broker_rationale_7", "target": "test_broker_test_broker_enforces_rate_limit", "relation": "rationale_for", "confidence": "EXTRACTED", "source_file": "C:\\Users\\point\\projects\\stockpredictor\\packages\\data\\tests\\test_broker.py", "source_location": "L7", "weight": 1.0}, {"source": "test_broker_rationale_28", "target": "test_broker_test_broker_rate_limits_when_saturated", "relation": "rationale_for", "confidence": "EXTRACTED", "source_file": "C:\\Users\\point\\projects\\stockpredictor\\packages\\data\\tests\\test_broker.py", "source_location": "L28", "weight": 1.0}]}